{"_id":"5a5c4fdf-027a-4993-80cc-78b0db4df1ea","title":"Movie Details","description":"Insights from the Movie Details dataset.","createdAt":{"$date":"2018-07-23T18:49:08.991Z"},"schemaVersion":0,"everyone":false,"viewers":[],"authors":[],"owners":["5b5622f1cc188900aadc016f"],"layout":[{"w":4,"h":2,"x":0,"y":0,"i":"3cd63045-f13a-47d7-a76b-daeb84a74a5a","minW":1,"maxW":10,"minH":1,"maxH":10,"moved":false,"static":false,"isDraggable":true,"isResizable":true},{"w":4,"h":2,"x":0,"y":2,"i":"12d6668d-4043-4f37-a082-90e45275818d","minW":1,"maxW":10,"minH":1,"maxH":10,"moved":false,"static":false,"isDraggable":true,"isResizable":true}],"itemSummary":[{"_id":"3cd63045-f13a-47d7-a76b-daeb84a74a5a","itemType":"chart","iconValue":"column-stacked","title":"Directors with Most Awards, Split by Genre","dataSourceId":"cfbb865f-358b-47f7-8c0f-199d7b5ceab3"},{"_id":"12d6668d-4043-4f37-a082-90e45275818d","itemType":"chart","iconValue":"scatter","title":"Movies with Most Awards Nominations, by Rating","dataSourceId":"cfbb865f-358b-47f7-8c0f-199d7b5ceab3"}],"lastModifiedAt":{"$date":"2018-07-23T18:53:59.858Z"},"permissionsSummary":{"text":"Dashboard Owner: You.\u003cbr /\u003eOnly you can access this dashboard.\u003cbr /\u003e","icon":"lock"}}
