{"_id":"05bda16b-3518-48cf-a5be-13500fbb6c87","title":"Movie Details","description":"Test","createdAt":{"$date":"2018-07-23T17:06:29.647Z"},"schemaVersion":0,"everyone":false,"viewers":[],"authors":[],"owners":["5b5609cdcc188900aab82978"],"layout":[{"i":"53af7adf-7ef4-4138-b7bd-70ec11f133e8","x":0,"y":0,"w":2,"h":2,"minW":1,"minH":1,"maxW":10,"maxH":10,"moved":false,"static":false,"isDraggable":true,"isResizable":true}],"itemSummary":[{"_id":"53af7adf-7ef4-4138-b7bd-70ec11f133e8","itemType":"chart","iconValue":"scatter","dataSourceId":"6370b952-4d7c-4a1c-859c-cfd7b2b2f8d5"}],"lastModifiedAt":{"$date":"2018-07-23T17:07:31.996Z"},"permissionsSummary":{"text":"Dashboard Owner: You.\u003cbr /\u003eOnly you can access this dashboard.\u003cbr /\u003e","icon":"lock"}}
